async_get_web/__init__.py
async_get_web/async_get_web.py
async_get_web/exceptions.py
async_get_web/validators.py
async_get_web-0.0.1.dist-info/AUTHORS.rst
async_get_web-0.0.1.dist-info/LICENSE
async_get_web-0.0.1.dist-info/METADATA
async_get_web-0.0.1.dist-info/WHEEL
async_get_web-0.0.1.dist-info/top_level.txt
async_get_web-0.0.1.dist-info/RECORD
