Metadata-Version: 2.1
Name: async-get-web
Version: 0.0.1
Summary: short_description
Home-page: https://github.com/ruslan-rv-ua/async_get_web
Author: Ruslan Iskov
Author-email: ruslan.rv.ua@gmail.com
License: MIT license
Keywords: async_get_web
Platform: UNKNOWN
Classifier: Development Status :: 2 - Pre-Alpha
Classifier: Intended Audience :: Developers
Classifier: License :: OSI Approved :: MIT License
Classifier: Natural Language :: English
Classifier: Programming Language :: Python :: 3
Classifier: Programming Language :: Python :: 3.7
Classifier: Programming Language :: Python :: 3.8
Requires-Python: >=3.7
Requires-Dist: requests-html (>=0.10)
Requires-Dist: pydantic (>=1.6)
